silk_cli/__init__.py
silk_cli/cli.py
silk_cli/commands/__init__.py
silk_cli/commands/cache.py
silk_cli/commands/config.py
silk_cli/commands/context.py
silk_cli/commands/init.py
silk_cli/commands/publish.py
silk_cli/commands/wordcount.py
silk_cli/core/__init__.py
silk_cli/core/cache.py
silk_cli/core/chapters.py
silk_cli/core/context.py
silk_cli/core/project.py
silk_cli/core/prompts.py
silk_cli/core/statistics.py
silk_cli/data/__init__.py
silk_cli/data/templates/__init__.py
silk_cli/data/templates/formats/base.yaml
silk_cli/data/templates/formats/book.yaml
silk_cli/data/templates/formats/digital.yaml
silk_cli/data/templates/formats/epub.yaml
silk_cli/data/templates/formats/html.yaml
silk_cli/data/templates/formats/iphone.yaml
silk_cli/data/templates/formats/kindle.yaml
silk_cli/models/__init__.py
silk_cli/models/chapter.py
silk_cli/models/config.py
silk_cli/publishing/__init__.py
silk_cli/publishing/pandoc.py
silk_cli/publishing/transformers.py
silk_cli/templates/__init__.py
silk_cli/templates/loader.py
silk_cli/tests/__init__.py
silk_cli/tests/conftest.py
silk_cli/tests/e2e/__init__.py
silk_cli/tests/e2e/test_e2e_cache.py
silk_cli/tests/e2e/test_e2e_config.py
silk_cli/tests/e2e/test_e2e_context.py
silk_cli/tests/e2e/test_e2e_init.py
silk_cli/tests/e2e/test_e2e_publish.py
silk_cli/tests/e2e/test_e2e_wordcount.py
silk_cli/tests/unit/__init__.py
silk_cli/tests/unit/test_cache.py
silk_cli/tests/unit/test_chapters.py
silk_cli/tests/unit/test_models.py
silk_cli/tests/unit/test_statistics.py
silk_cli/tests/unit/test_transformers.py
silk_cli/utils/__init__.py
silk_cli/utils/console.py
silk_cli-2.0.0.dist-info/METADATA
silk_cli-2.0.0.dist-info/WHEEL
silk_cli-2.0.0.dist-info/entry_points.txt
silk_cli-2.0.0.dist-info/licenses/LICENSE
silk_cli-2.0.0.dist-info/RECORD
