Metadata-Version: 2.4
Name: silk-cli
Version: 2.0.0
Summary: Smart Integrated Literary Kit - Modern CLI for authors with LLM integration
License: MIT
License-File: LICENSE
Keywords: cli,writing,manuscript,llm,author,novel
Author: Antoine Sauvinet
Requires-Python: >=3.11,<4.0
Classifier: Development Status :: 4 - Beta
Classifier: Environment :: Console
Classifier: Intended Audience :: End Users/Desktop
Classifier: License :: OSI Approved :: MIT License
Classifier: Programming Language :: Python :: 3
Classifier: Programming Language :: Python :: 3.11
Classifier: Programming Language :: Python :: 3.12
Classifier: Programming Language :: Python :: 3.13
Classifier: Programming Language :: Python :: 3.14
Classifier: Topic :: Artistic Software
Classifier: Topic :: Text Processing
Requires-Dist: pydantic (>=2.5,<3.0)
Requires-Dist: pyyaml (>=6.0,<7.0)
Requires-Dist: rich (>=13.7,<14.0)
Requires-Dist: typer[all] (>=0.16,<0.17)
Project-URL: Repository, https://github.com/oinant/silk-cli
